ebrains_drive/__init__.py
ebrains_drive/_version.py
ebrains_drive/admin.py
ebrains_drive/bucket.py
ebrains_drive/buckets.py
ebrains_drive/client.py
ebrains_drive/exceptions.py
ebrains_drive/file.py
ebrains_drive/files.py
ebrains_drive/group.py
ebrains_drive/repo.py
ebrains_drive/repos.py
ebrains_drive/utils.py
ebrains_drive-0.6.1.dist-info/licenses/LICENSE
ebrains_drive-0.6.1.dist-info/METADATA
ebrains_drive-0.6.1.dist-info/WHEEL
ebrains_drive-0.6.1.dist-info/top_level.txt
ebrains_drive-0.6.1.dist-info/RECORD
