Metadata-Version: 2.4
Name: ebrains-drive
Version: 0.6.1
Summary: Python client interface for EBRAINS Collaboratory Drive and Bucket storage
Author-email: EBRAINS <support@ebrains.eu>
Maintainer-email: EBRAINS <support@ebrains.eu>
License-Expression: Apache-2.0
Project-URL: documentation, https://github.com/HumanBrainProject/ebrains-storage/blob/master/doc.md
Project-URL: repository, https://github.com/HumanBrainProject/ebrains-storage
Project-URL: download, https://pypi.org/project/ebrains-drive/
Classifier: Development Status :: 4 - Beta
Classifier: Intended Audience :: Science/Research
Classifier: Operating System :: OS Independent
Classifier: Programming Language :: Python
Classifier: Topic :: Scientific/Engineering
Requires-Python: >=3.9
License-File: LICENSE
Requires-Dist: requests
Requires-Dist: tqdm
Provides-Extra: test
Requires-Dist: pytest; extra == "test"
Requires-Dist: pytest-cov; extra == "test"
Requires-Dist: wheel; extra == "test"
Dynamic: license-file
